setup.py
huaweicloud_sdk_python_obs.egg-info/PKG-INFO
huaweicloud_sdk_python_obs.egg-info/SOURCES.txt
huaweicloud_sdk_python_obs.egg-info/dependency_links.txt
huaweicloud_sdk_python_obs.egg-info/not-zip-safe
huaweicloud_sdk_python_obs.egg-info/requires.txt
huaweicloud_sdk_python_obs.egg-info/top_level.txt
obs/__init__.py
obs/auth.py
obs/bucket.py
obs/bulktasks.py
obs/cache.py
obs/client.py
obs/const.py
obs/convertor.py
obs/crypto_client.py
obs/extension.py
obs/http2.py
obs/ilog.py
obs/loadtoken.py
obs/locks.py
obs/model.py
obs/obs_cipher_suite.py
obs/progress.py
obs/searchmethod.py
obs/transfer.py
obs/util.py
obs/workflow.py