Metadata-Version: 1.0
Name: huaweicloud-sdk-python-obs
Version: 3.21.8
Summary: OBS Python SDK
Home-page: UNKNOWN
Author: UNKNOWN
Author-email: UNKNOWN
License: Apache-2.0
Keywords: obs
Platform: Independant
